iaode/BEN.py
iaode/DRE.py
iaode/LSE.py
iaode/__init__.py
iaode/agent.py
iaode/annotation.py
iaode/datasets.py
iaode/environment.py
iaode/mixin.py
iaode/model.py
iaode/module.py
iaode/utils.py
iaode-0.2.9.dist-info/licenses/LICENSE
iaode-0.2.9.dist-info/METADATA
iaode-0.2.9.dist-info/WHEEL
iaode-0.2.9.dist-info/top_level.txt
iaode-0.2.9.dist-info/RECORD
