Metadata-Version: 2.4
Name: iaode
Version: 0.2.9
Summary: Interpretable Autoencoder with Ordinary Differential Equations for single-cell omics analysis
Author-email: Zeyu Fu <fuzeyu99@126.com>
License-Expression: MIT
Project-URL: Homepage, https://github.com/PeterPonyu/iAODE
Project-URL: Documentation, https://iaode.readthedocs.io
Project-URL: Repository, https://github.com/PeterPonyu/iAODE
Project-URL: Bug Tracker, https://github.com/PeterPonyu/iAODE/issues
Keywords: single-cell,omics,dimensionality-reduction,neural-ode,variational-autoencoder,trajectory-inference,scRNA-seq,scATAC-seq
Classifier: Development Status :: 3 - Alpha
Classifier: Intended Audience :: Science/Research
Classifier: Operating System :: OS Independent
Classifier: Programming Language :: Python :: 3
Classifier: Programming Language :: Python :: 3.9
Classifier: Programming Language :: Python :: 3.10
Classifier: Programming Language :: Python :: 3.11
Classifier: Programming Language :: Python :: 3.12
Classifier: Topic :: Scientific/Engineering :: Bio-Informatics
Classifier: Topic :: Scientific/Engineering :: Artificial Intelligence
Requires-Python: >=3.9
License-File: LICENSE
Requires-Dist: numpy>=1.20.0
Requires-Dist: pandas>=1.3.0
Requires-Dist: scipy>=1.7.0
Requires-Dist: scikit-learn>=1.0.0
Requires-Dist: torch>=1.10.0
Requires-Dist: torchdiffeq>=0.2.0
Requires-Dist: anndata>=0.8.0
Requires-Dist: scanpy>=1.8.0
Requires-Dist: scvi-tools>=0.16.0
Requires-Dist: requests>=2.25.0
Requires-Dist: tqdm>=4.60.0
Provides-Extra: dev
Requires-Dist: pytest>=7.0.0; extra == "dev"
Requires-Dist: pytest-cov>=3.0.0; extra == "dev"
Requires-Dist: black>=22.0.0; extra == "dev"
Requires-Dist: flake8>=4.0.0; extra == "dev"
Requires-Dist: mypy>=0.950; extra == "dev"
Requires-Dist: build>=0.7.0; extra == "dev"
Requires-Dist: twine>=4.0.0; extra == "dev"
Provides-Extra: docs
Requires-Dist: sphinx>=4.5.0; extra == "docs"
Requires-Dist: sphinx-rtd-theme>=1.0.0; extra == "docs"
Requires-Dist: sphinx-autodoc-typehints>=1.18.0; extra == "docs"
Dynamic: license-file
